{
  "log_likelihood": 20007.61188334383,
  "training_accuracy": 0.4476439790575916,
  "regime_accuracies": {
    "0": 0.0,
    "1": 0.27586206896551724,
    "2": 0.9655172413793104,
    "3": 0.20224719101123595,
    "4": 0.07246376811594203
  },
  "average_confidence": 1.0,
  "state_to_regime": {
    "0": 3,
    "1": 1,
    "2": 3,
    "3": 3,
    "4": 3,
    "5": 2,
    "6": 2,
    "7": 4,
    "8": 1
  },
  "state_confidence": {
    "0": 1.0,
    "1": 1.0,
    "2": 1.0,
    "3": 1.0,
    "4": 1.0,
    "5": 1.0,
    "6": 1.0,
    "7": 1.0,
    "8": 1.0
  },
  "selected_features": [
    "return_std",
    "return_max",
    "return_min",
    "realized_volatility",
    "price_change_std",
    "max_price_change",
    "rolling_vol_short",
    "rolling_vol_medium",
    "volatility_of_volatility",
    "price_level_volatility",
    "vol_p25",
    "vol_p50",
    "vol_p75",
    "vol_p90",
    "price_momentum",
    "price_momentum_medium",
    "price_acceleration",
    "velocity_consistency",
    "early_momentum",
    "late_momentum",
    "momentum_acceleration",
    "final_momentum_strength",
    "price_coefficient_variation",
    "avg_price_gap",
    "rel_price_std"
  ],
  "n_components": 9,
  "n_features": 25,
  "covariance_type": "full",
  "successful_trials": 60,
  "total_trials": 60
}