{
  "feature_names": [
    "rel_price_mean",
    "rel_price_std",
    "rel_price_min",
    "rel_price_max",
    "rel_price_range",
    "rel_price_range_pct",
    "return_mean",
    "return_std",
    "return_skewness",
    "return_kurtosis",
    "realized_volatility",
    "rel_price_change_std",
    "max_rel_price_change",
    "rel_rolling_vol_mean",
    "rel_rolling_vol_std",
    "rel_rolling_vol_max",
    "rel_momentum_mean",
    "rel_momentum_std",
    "rel_momentum_final",
    "rel_trend_slope",
    "rel_trend_r_squared",
    "rel_trend_p_value",
    "rel_trend_strength",
    "direction_changes",
    "direction_consistency",
    "num_peaks",
    "num_troughs",
    "peak_trough_ratio",
    "reversal_frequency",
    "autocorr_lag1",
    "num_jumps",
    "jump_frequency",
    "max_jump_size",
    "overnight_gap_absolute",
    "overnight_gap_percentage",
    "overnight_gap_positive_x",
    "overnight_gap_magnitude",
    "overnight_gap",
    "overnight_gap_abs",
    "overnight_gap_positive_y",
    "overnight_gap_size",
    "large_gap_up",
    "large_gap_down",
    "small_gap"
  ],
  "trading_start_ms": 34200000,
  "trading_end_ms": 43200000,
  "reference_time_ms": 34200000,
  "include_overnight_gap": true,
  "overnight_indicators": false,
  "n_regimes": 7,
  "total_days": 1407,
  "note": "All price-based features calculated as percentage change from reference time (09:30). Overnight gaps included. Overnight indicators disabled."
}